yousign3/client.py
yousign3/constants.py
yousign3/datasets.py
yousign3/rest/endpoint.py
yousign3/rest/request_handler.py
yousign3/type/approvers.py
yousign3/type/document.py
yousign3/type/field.py
yousign3/type/fields/checkbox.py
yousign3/type/fields/mention.py
yousign3/type/fields/radiogroup.py
yousign3/type/fields/signature.py
yousign3/type/fields/text.py
yousign3/type/label.py
yousign3/type/signature.py
yousign3/type/signer.py
yousign3-0.0.6.dist-info/METADATA
yousign3-0.0.6.dist-info/WHEEL
yousign3-0.0.6.dist-info/licenses/LICENSE
yousign3-0.0.6.dist-info/RECORD
